toggl.py
toggl_api.py
toggl_cli-3.data/data/config.yml
toggl_cli-3.dist-info/DESCRIPTION.rst
toggl_cli-3.dist-info/METADATA
toggl_cli-3.dist-info/RECORD
toggl_cli-3.dist-info/WHEEL
toggl_cli-3.dist-info/entry_points.txt
toggl_cli-3.dist-info/metadata.json
toggl_cli-3.dist-info/top_level.txt
